spyder_unittest/__init__.py
spyder_unittest/unittestplugin.py
spyder_unittest/backend/__init__.py
spyder_unittest/backend/abbreviator.py
spyder_unittest/backend/frameworkregistry.py
spyder_unittest/backend/nose2runner.py
spyder_unittest/backend/pytestrunner.py
spyder_unittest/backend/runnerbase.py
spyder_unittest/backend/unittestrunner.py
spyder_unittest/backend/zmqreader.py
spyder_unittest/backend/tests/__init__.py
spyder_unittest/backend/tests/test_abbreviator.py
spyder_unittest/backend/tests/test_frameworkregistry.py
spyder_unittest/backend/tests/test_nose2runner.py
spyder_unittest/backend/tests/test_pytestrunner.py
spyder_unittest/backend/tests/test_runnerbase.py
spyder_unittest/backend/tests/test_unittestrunner.py
spyder_unittest/backend/tests/test_zmqstream.py
spyder_unittest/backend/workers/__init__.py
spyder_unittest/backend/workers/print_versions.py
spyder_unittest/backend/workers/pytestworker.py
spyder_unittest/backend/workers/unittestworker.py
spyder_unittest/backend/workers/zmqwriter.py
spyder_unittest/backend/workers/tests/test_print_versions.py
spyder_unittest/backend/workers/tests/test_pytestworker.py
spyder_unittest/backend/workers/tests/test_unittestworker.py
spyder_unittest/locale/de/LC_MESSAGES/spyder_unittest.mo
spyder_unittest/locale/es/LC_MESSAGES/spyder_unittest.mo
spyder_unittest/locale/fr/LC_MESSAGES/spyder_unittest.mo
spyder_unittest/locale/hr/LC_MESSAGES/spyder_unittest.mo
spyder_unittest/locale/hu/LC_MESSAGES/spyder_unittest.mo
spyder_unittest/locale/ja/LC_MESSAGES/spyder_unittest.mo
spyder_unittest/locale/pl/LC_MESSAGES/spyder_unittest.mo
spyder_unittest/locale/pt_BR/LC_MESSAGES/spyder_unittest.mo
spyder_unittest/locale/ru/LC_MESSAGES/spyder_unittest.mo
spyder_unittest/locale/zh_CN/LC_MESSAGES/spyder_unittest.mo
spyder_unittest/tests/conftest.py
spyder_unittest/tests/test_unittestplugin.py
spyder_unittest/widgets/__init__.py
spyder_unittest/widgets/configdialog.py
spyder_unittest/widgets/confpage.py
spyder_unittest/widgets/datatree.py
spyder_unittest-0.7.1.dist-info/licenses/LICENSE.txt
spyder_unittest-0.7.1.dist-info/METADATA
spyder_unittest-0.7.1.dist-info/WHEEL
spyder_unittest-0.7.1.dist-info/entry_points.txt
spyder_unittest-0.7.1.dist-info/top_level.txt
spyder_unittest-0.7.1.dist-info/RECORD
