Metadata-Version: 2.4
Name: spyder-unittest
Version: 0.7.1
Summary: Plugin to run tests from within the Spyder IDE
Author: Spyder Project Contributors
License-Expression: MIT
Project-URL: source, https://github.com/spyder-ide/spyder-unittest
Keywords: Qt,PyQt5,PyQt6,spyder,plugins,testing
Classifier: Development Status :: 4 - Beta
Classifier: Environment :: X11 Applications :: Qt
Classifier: Environment :: Win32 (MS Windows)
Classifier: Intended Audience :: Developers
Classifier: Operating System :: OS Independent
Classifier: Programming Language :: Python :: 3
Classifier: Programming Language :: Python :: 3.10
Classifier: Programming Language :: Python :: 3.11
Classifier: Programming Language :: Python :: 3.12
Classifier: Topic :: Software Development :: Testing
Classifier: Topic :: Text Editors :: Integrated Development Environments (IDE)
Requires-Python: >=3.10
License-File: LICENSE.txt
Requires-Dist: lxml
Requires-Dist: spyder<7,>=6
Requires-Dist: pyzmq
Dynamic: license-file
